flask_openipa/__init__.py
flask_openipa/blueprint.py
flask_openipa/defaults.py
flask_openipa/exceptions.py
flask_openipa/extension.py
flask_openipa/openapi.py
flask_openipa-0.0.4.dist-info/METADATA
flask_openipa-0.0.4.dist-info/WHEEL
flask_openipa-0.0.4.dist-info/top_level.txt
flask_openipa-0.0.4.dist-info/RECORD
